odoo8_addon_business_requirement_deliverable_crm-8.0.1.0.1.99.dev14-py3.8-nspkg.pth
odoo_addons/business_requirement_deliverable_crm/README.rst
odoo_addons/business_requirement_deliverable_crm/__init__.py
odoo_addons/business_requirement_deliverable_crm/__openerp__.py
odoo_addons/business_requirement_deliverable_crm/data/business_requirement_deliverable_crm_demo.xml
odoo_addons/business_requirement_deliverable_crm/i18n/business_requirement_deliverable_crm.pot
odoo_addons/business_requirement_deliverable_crm/i18n/fr.po
odoo_addons/business_requirement_deliverable_crm/i18n/sl.po
odoo_addons/business_requirement_deliverable_crm/models/__init__.py
odoo_addons/business_requirement_deliverable_crm/models/crm.py
odoo_addons/business_requirement_deliverable_crm/static/description/icon.png
odoo_addons/business_requirement_deliverable_crm/tests/__init__.py
odoo_addons/business_requirement_deliverable_crm/tests/test_br.py
odoo_addons/business_requirement_deliverable_crm/tests/test_wizard_br.py
odoo_addons/business_requirement_deliverable_crm/views/crm_view.xml
odoo_addons/business_requirement_deliverable_crm/wizard/__init__.py
odoo_addons/business_requirement_deliverable_crm/wizard/crm_make_sale.py
odoo_addons/business_requirement_deliverable_crm/wizard/crm_make_sale_view.xml
odoo8_addon_business_requirement_deliverable_crm-8.0.1.0.1.99.dev14.dist-info/METADATA
odoo8_addon_business_requirement_deliverable_crm-8.0.1.0.1.99.dev14.dist-info/WHEEL
odoo8_addon_business_requirement_deliverable_crm-8.0.1.0.1.99.dev14.dist-info/namespace_packages.txt
odoo8_addon_business_requirement_deliverable_crm-8.0.1.0.1.99.dev14.dist-info/top_level.txt
odoo8_addon_business_requirement_deliverable_crm-8.0.1.0.1.99.dev14.dist-info/RECORD
